[
  {
    "value": 36100000.0,
    "time": 1568561930
  },
  {
    "value": 36200000.0,
    "time": 1568561940
  },
  {
    "value": 36200000.0,
    "time": 1568561950
  },
  {
    "value": 36300000.0,
    "time": 1568561960
  },
  {
    "value": 36300000.0,
    "time": 1568561970
  },
  {
    "value": 36300000.0,
    "time": 1568561980
  },
  {
    "value": 36400000.0,
    "time": 1568561990
  },
  {
    "value": 36400000.0,
    "time": 1568562000
  },
  {
    "value": 36500000.0,
    "time": 1568562010
  },
  {
    "value": 36500000.0,
    "time": 1568562020
  },
  {
    "value": 36500000.0,
    "time": 1568562030
  },
  {
    "value": 36600000.0,
    "time": 1568562040
  },
  {
    "value": 36600000.0,
    "time": 1568562050
  },
  {
    "value": 36700000.0,
    "time": 1568562060
  },
  {
    "value": 36700000.0,
    "time": 1568562070
  },
  {
    "value": 36800000.0,
    "time": 1568562080
  },
  {
    "value": 36800000.0,
    "time": 1568562090
  },
  {
    "value": 36800000.0,
    "time": 1568562100
  },
  {
    "value": 36900000.0,
    "time": 1568562110
  },
  {
    "value": 36900000.0,
    "time": 1568562120
  },
  {
    "value": 37000000.0,
    "time": 1568562130
  },
  {
    "value": 37000000.0,
    "time": 1568562140
  },
  {
    "value": 37100000.0,
    "time": 1568562150
  },
  {
    "value": 37100000.0,
    "time": 1568562160
  },
  {
    "value": 37100000.0,
    "time": 1568562170
  },
  {
    "value": 37200000.0,
    "time": 1568562180
  },
  {
    "value": 37200000.0,
    "time": 1568562190
  },
  {
    "value": 37300000.0,
    "time": 1568562200
  },
  {
    "value": 37300000.0,
    "time": 1568562210
  },
  {
    "value": 37300000.0,
    "time": 1568562220
  },
  {
    "value": 37400000.0,
    "time": 1568562230
  },
  {
    "value": 37400000.0,
    "time": 1568562240
  },
  {
    "value": 37500000.0,
    "time": 1568562250
  },
  {
    "value": 37500000.0,
    "time": 1568562260
  },
  {
    "value": 37500000.0,
    "time": 1568562270
  },
  {
    "value": 37600000.0,
    "time": 1568562280
  },
  {
    "value": 37600000.0,
    "time": 1568562290
  },
  {
    "value": 37700000.0,
    "time": 1568562300
  },
  {
    "value": 37700000.0,
    "time": 1568562310
  },
  {
    "value": 37700000.0,
    "time": 1568562320
  },
  {
    "value": 37800000.0,
    "time": 1568562330
  },
  {
    "value": 37800000.0,
    "time": 1568562340
  },
  {
    "value": 37900000.0,
    "time": 1568562350
  },
  {
    "value": 37900000.0,
    "time": 1568562360
  },
  {
    "value": 37900000.0,
    "time": 1568562370
  },
  {
    "value": 38000000.0,
    "time": 1568562380
  },
  {
    "value": 38000000.0,
    "time": 1568562390
  },
  {
    "value": 38100000.0,
    "time": 1568562400
  },
  {
    "value": 38100000.0,
    "time": 1568562410
  },
  {
    "value": 38100000.0,
    "time": 1568562420
  },
  {
    "value": 38200000.0,
    "time": 1568562430
  },
  {
    "value": 38200000.0,
    "time": 1568562440
  },
  {
    "value": 38300000.0,
    "time": 1568562450
  },
  {
    "value": 38300000.0,
    "time": 1568562460
  },
  {
    "value": 38300000.0,
    "time": 1568562470
  },
  {
    "value": 38400000.0,
    "time": 1568562480
  },
  {
    "value": 38400000.0,
    "time": 1568562490
  },
  {
    "value": 38400000.0,
    "time": 1568562500
  },
  {
    "value": 38500000.0,
    "time": 1568562510
  },
  {
    "value": 38500000.0,
    "time": 1568562520
  },
  {
    "value": 38600000.0,
    "time": 1568562530
  },
  {
    "value": 38600000.0,
    "time": 1568562540
  },
  {
    "value": 38600000.0,
    "time": 1568562550
  },
  {
    "value": 38700000.0,
    "time": 1568562560
  },
  {
    "value": 38700000.0,
    "time": 1568562570
  },
  {
    "value": 38800000.0,
    "time": 1568562580
  },
  {
    "value": 38800000.0,
    "time": 1568562590
  },
  {
    "value": 38800000.0,
    "time": 1568562600
  },
  {
    "value": 38900000.0,
    "time": 1568562610
  },
  {
    "value": 38900000.0,
    "time": 1568562620
  },
  {
    "value": 39000000.0,
    "time": 1568562630
  },
  {
    "value": 39000000.0,
    "time": 1568562640
  },
  {
    "value": 39000000.0,
    "time": 1568562650
  },
  {
    "value": 39100000.0,
    "time": 1568562660
  },
  {
    "value": 39100000.0,
    "time": 1568562670
  },
  {
    "value": 39200000.0,
    "time": 1568562680
  },
  {
    "value": 39200000.0,
    "time": 1568562690
  },
  {
    "value": 39200000.0,
    "time": 1568562700
  },
  {
    "value": 39300000.0,
    "time": 1568562710
  },
  {
    "value": 39300000.0,
    "time": 1568562720
  },
  {
    "value": 39400000.0,
    "time": 1568562730
  },
  {
    "value": 39400000.0,
    "time": 1568562740
  },
  {
    "value": 39400000.0,
    "time": 1568562750
  },
  {
    "value": 39500000.0,
    "time": 1568562760
  },
  {
    "value": 39500000.0,
    "time": 1568562770
  },
  {
    "value": 39500000.0,
    "time": 1568562780
  },
  {
    "value": 39600000.0,
    "time": 1568562790
  },
  {
    "value": 39600000.0,
    "time": 1568562800
  },
  {
    "value": 39700000.0,
    "time": 1568562810
  },
  {
    "value": 39700000.0,
    "time": 1568562820
  },
  {
    "value": 39700000.0,
    "time": 1568562830
  },
  {
    "value": 39800000.0,
    "time": 1568562840
  },
  {
    "value": 39800000.0,
    "time": 1568562850
  },
  {
    "value": 39900000.0,
    "time": 1568562860
  },
  {
    "value": 39900000.0,
    "time": 1568562870
  },
  {
    "value": 39900000.0,
    "time": 1568562880
  },
  {
    "value": 40000000.0,
    "time": 1568562890
  },
  {
    "value": 40000000.0,
    "time": 1568562900
  },
  {
    "value": 40000000.0,
    "time": 1568562910
  },
  {
    "value": 40100000.0,
    "time": 1568562920
  },
  {
    "value": 40100000.0,
    "time": 1568562930
  },
  {
    "value": 40100000.0,
    "time": 1568562940
  },
  {
    "value": 40200000.0,
    "time": 1568562950
  },
  {
    "value": 40200000.0,
    "time": 1568562960
  },
  {
    "value": 40300000.0,
    "time": 1568562970
  },
  {
    "value": 40300000.0,
    "time": 1568562980
  },
  {
    "value": 40300000.0,
    "time": 1568562990
  },
  {
    "value": 40400000.0,
    "time": 1568563000
  },
  {
    "value": 40400000.0,
    "time": 1568563010
  },
  {
    "value": 40400000.0,
    "time": 1568563020
  },
  {
    "value": 40500000.0,
    "time": 1568563030
  },
  {
    "value": 40500000.0,
    "time": 1568563040
  },
  {
    "value": 40600000.0,
    "time": 1568563050
  },
  {
    "value": 40600000.0,
    "time": 1568563060
  },
  {
    "value": 40700000.0,
    "time": 1568563070
  },
  {
    "value": 40700000.0,
    "time": 1568563080
  },
  {
    "value": 40700000.0,
    "time": 1568563090
  },
  {
    "value": 40800000.0,
    "time": 1568563100
  },
  {
    "value": 40800000.0,
    "time": 1568563110
  },
  {
    "value": 40800000.0,
    "time": 1568563120
  },
  {
    "value": 40800000.0,
    "time": 1568563130
  }
]