[
  {
    "value": 0.0,
    "time": 1568585030
  },
  {
    "value": 0.0,
    "time": 1568585040
  },
  {
    "value": 0.0,
    "time": 1568585050
  },
  {
    "value": 41200.0,
    "time": 1568585060
  },
  {
    "value": 95800.0,
    "time": 1568585070
  },
  {
    "value": 146000.0,
    "time": 1568585080
  },
  {
    "value": 203000.0,
    "time": 1568585090
  },
  {
    "value": 255000.0,
    "time": 1568585100
  },
  {
    "value": 311000.0,
    "time": 1568585110
  },
  {
    "value": 360000.0,
    "time": 1568585120
  },
  {
    "value": 408000.0,
    "time": 1568585130
  },
  {
    "value": 443000.0,
    "time": 1568585140
  },
  {
    "value": 496000.0,
    "time": 1568585150
  },
  {
    "value": 532000.0,
    "time": 1568585160
  },
  {
    "value": 587000.0,
    "time": 1568585170
  },
  {
    "value": 632000.0,
    "time": 1568585180
  },
  {
    "value": 689000.0,
    "time": 1568585190
  },
  {
    "value": 739000.0,
    "time": 1568585200
  },
  {
    "value": 789000.0,
    "time": 1568585210
  },
  {
    "value": 836000.0,
    "time": 1568585220
  },
  {
    "value": 885000.0,
    "time": 1568585230
  },
  {
    "value": 927000.0,
    "time": 1568585240
  },
  {
    "value": 967000.0,
    "time": 1568585250
  },
  {
    "value": 1010000.0,
    "time": 1568585260
  },
  {
    "value": 1060000.0,
    "time": 1568585270
  },
  {
    "value": 1110000.0,
    "time": 1568585280
  },
  {
    "value": 1150000.0,
    "time": 1568585290
  },
  {
    "value": 1200000.0,
    "time": 1568585300
  },
  {
    "value": 1250000.0,
    "time": 1568585310
  },
  {
    "value": 1290000.0,
    "time": 1568585320
  },
  {
    "value": 1340000.0,
    "time": 1568585330
  },
  {
    "value": 1390000.0,
    "time": 1568585340
  },
  {
    "value": 1440000.0,
    "time": 1568585350
  },
  {
    "value": 1480000.0,
    "time": 1568585360
  },
  {
    "value": 1510000.0,
    "time": 1568585370
  },
  {
    "value": 1560000.0,
    "time": 1568585380
  },
  {
    "value": 1600000.0,
    "time": 1568585390
  },
  {
    "value": 1650000.0,
    "time": 1568585400
  },
  {
    "value": 1710000.0,
    "time": 1568585410
  },
  {
    "value": 1750000.0,
    "time": 1568585420
  },
  {
    "value": 1790000.0,
    "time": 1568585430
  },
  {
    "value": 1840000.0,
    "time": 1568585440
  },
  {
    "value": 1890000.0,
    "time": 1568585450
  },
  {
    "value": 1940000.0,
    "time": 1568585460
  },
  {
    "value": 1970000.0,
    "time": 1568585470
  },
  {
    "value": 2020000.0,
    "time": 1568585480
  },
  {
    "value": 2049999.0,
    "time": 1568585490
  },
  {
    "value": 2100000.0,
    "time": 1568585500
  },
  {
    "value": 2140000.0,
    "time": 1568585510
  },
  {
    "value": 2190000.0,
    "time": 1568585520
  },
  {
    "value": 2230000.0,
    "time": 1568585530
  },
  {
    "value": 2290000.0,
    "time": 1568585540
  },
  {
    "value": 2340000.0,
    "time": 1568585550
  },
  {
    "value": 2380000.0,
    "time": 1568585560
  },
  {
    "value": 2430000.0,
    "time": 1568585570
  },
  {
    "value": 2470000.0,
    "time": 1568585580
  }
]